Workbook
Name ListaIngredientes: 'Materia Prima'!$B$3:$B$194

Sheet Materia Prima
A1: ID único en Supabase | B1: Nombre del producto como aparece en el sistema | C1: Unidad en la que se lleva el inventario (stock) | D1: Categoría del producto | E1: Precio por 1 unidad de stock (USD) | F1: ¿Producto activo? | G1: ¿Aparece en conteo nocturno? | H1: Stock total actual (todas las sucursales)
A2: id | B2: nombre | C2: unidad_stock | D2: categoria | E2: precio_unit | F2: activo | G2: en_conteo | H2: stock_total
A3: fdd67993-4f0f-447c-8466-2b791ed3bcc1 | B3: 1250 Margarina | C3: Unidad | D3: Insumo Cocina | E3: 9.55 | F3: TRUE | G3: FALSE | H3: 0
A4: 0b216432-013b-4ee7-851e-2f4964232329 | B4: 1250 Tomates | C4: lata | D4: Insumo Cocina | E4: 7.07 | F4: TRUE | G4: FALSE | H4: 0
A5: a75ccc77-0209-4828-a446-689d8db6f1a9 | B5: 16100 Pepinillos | C5: Unidad | D5: Insumo Hamburguesa | E5: 5.74 | F5: TRUE | G5: FALSE | H5: 0
A6: 319db2d5-9f6e-4f1f-995b-3a8fd4824bc2 | B6: 2032 Puyazo Gold | C6: lb | D6: Insumo Hamburguesa | E6: 7.52 | F6: TRUE | G6: FALSE | H6: 0
A7: 6b97ab93-966d-49c6-afaa-ead21d1c9b80 | B7: 228941 Pepinillos | C7: oz | D7: Insumo Hamburguesa | E7: 5.74 | F7: TRUE | G7: FALSE | H7: 0
A8: c9d2b671-68b8-46bf-92c3-1ef2a09e8d88 | B8: 278946 Salsa Inglesa | C8: botella | D8: Insumo Cocina | E8: 7.07 | F8: TRUE | G8: FALSE | H8: 0
A9: 07869bf2-a1b9-4d03-8faa-6d23f10824b8 | B9: 30204 Oregano | C9: g | D9: Insumo Cocina | E9: 5.12 | F9: TRUE | G9: FALSE | H9: 0
A10: 1a82893b-f124-41a8-a8fb-b17480143d3e | B10: 325026-MCX03621 MC REDSTONE | C10: Caja | D10: Insumo Papas | E10: 38 | F10: TRUE | G10: FALSE | H10: 0
A11: d32fe707-b0de-4c8b-a8ca-037e611294b5 | B11: 325052-MCF03788 MCC SCP 3 8 | C11: Caja | D11: Insumo Extras | E11: 38 | F11: TRUE | G11: FALSE | H11: 0
A12: 95e81726-03a8-4722-b3bc-a42b347fac7c | B12: 326235 Azucar Morena | C12: g | D12: Insumo Extras | E12: 7.25 | F12: TRUE | G12: FALSE | H12: 0
A13: 0162232b-026d-4e3a-8efd-f62027f500bc | B13: 352613 Jalisco | C13: Unidad | D13: Insumo Extras | E13: 13.97 | F13: TRUE | G13: FALSE | H13: 0
A14: 54f4b398-f14b-4c7d-bda8-0a7547f5d62b | B14: 524550 Ajo Granulado | C14: g | D14: Insumo Cocina | E14: 7.51 | F14: TRUE | G14: FALSE | H14: 0
... A54: eb731bbd-75f9-48d4-8cf7-0ab3761beb83 | B54: Cebolla morada bolsa 2 lbs | C54: bolsa | D54: Vegetales y Verduras | E54: 0 | F54: TRUE | G54: TRUE | H54: 0
A55: ecefa37d-e2df-4564-9e97-635c4eab9805 | B55: Cheddar Lata | C55: lata | D55: Salsas y Aderezos | E55: 0 | F55: TRUE | H55: 0
A56: 648e4f72-c088-44dd-8984-fe3f307b9bfa | B56: Cheddar Porcionado | C56: bolsa | D56: Sub Producto | E56: 0 | F56: TRUE | G56: TRUE | H56: 0
A57: 95c10e30-287e-465e-b3f2-0b66c121ce7d | B57: Chile Chipotle Adobado 24/380 GR | C57: lata | D57: Insumo Extras | E57: 2.43 | F57: TRUE | G57: FALSE | H57: 0
A58: a017d502-86e0-49ab-b830-fe9bfaa50524 | B58: Chile Molido | C58: cucharada | D58: Insumo Cocina | E58: 0 | F58: TRUE | G58: FALSE | H58: 0
A59: 00033f61-8d22-4e1d-ac18-bd338c9cfdb6 | B59: Chile Verde Mercado | C59: Unidad | D59: Insumo Cocina | E59: 0.88 | F59: TRUE | G59: FALSE | H59: 0
A60: a3b30e67-8a47-492f-a300-5678043f6843 | B60: Chile verde | C60: unidad | D60: Insumo | E60: 5 | F60: TRUE | G60: FALSE | H60: 0
A61: 18aa0ec1-5ee5-4af9-a429-ef30e8fcc582 | B61: Chili bolsa | C61: bolsa | D61: Carnes y Complementos | E61: 0 | F61: TRUE | G61: TRUE | H61: 0
A62: c3e6a382-6d74-4502-9fda-2845058a4f7a | B62: Chipotle bolsa | C62: bolsa | D62: Salsas y Aderezos | E62: 0 | F62: TRUE | G62: TRUE | H62: 0
A63: 4c557728-6e30-4fd1-b49b-7774caf86c2f | B63: Cilantro badia bote 99.2 gr | C63: bote | D63: Salsas y Aderezos | E63: 0 | F63: TRUE | G63: TRUE | H63: 0
A64: 779f3719-bf02-46a5-935d-3ce0763cbffe | B64: Cocoa en Polvo | C64: cucharadita | D64: Insumo Cocina | E64: 0 | F64: TRUE | G64: FALSE | H64: 0
A65: 81106def-30cf-4d21-aa99-d3e1c191adb7 | B65: Comino Molido | C65: cucharadita | D65: Insumo Cocina | E65: 0 | F65: TRUE | G65: FALSE | H65: 0
A66: 1f99c20e-61e2-4cfc-a36b-0dd62f23d511 | B66: Coronitas adivina la marca paquete 200 unidades | C66: paquete | D66: Extras | E66: 0 | F66: TRUE | G66: TRUE | H66: 0
A67: 0e5d7b7f-ae11-4a96-a0c7-883b719d4e60 | B67: Costilla Sparib | C67: lb | D67: Carnes | E67: 2.77 | F67: TRUE | G67: FALSE | H67: 0
... A194: 4caa7913-5004-4ca7-9b0c-8595155d9336 | B194: tenedor gande superpac blanco 5x40x25 | C194: unidad | D194: insumo | E194: 0.25 | F194: TRUE | G194: FALSE | H194: 0

Sheet Sub-Productos
A1: Nombre del sub-producto | B1: Ingrediente (seleccionar de lista Materia Prima) | C1: Cantidad por lote/tanda | D1: Unidad del ingrediente | E1: =BUSCARV del precio desde Materia Prima | F1: =cantidad × precio_unit | G1: Rendimiento (cuántas porciones salen del lote) | H1: Unidad del rendimiento | I1: =costo_total_lote / rendimiento
A2: sub_producto | B2: ingrediente | C2: cantidad | D2: unidad | E2: precio_unit | F2: costo_linea | G2: rendimiento | H2: unidad_rend | I2: costo_por_porcion
A3: Cebolla Blanca | G3: 10 | H3: bolsa
B4: Cebollas Blancas | C4: 20 | D4: unidad | E4: =IFERROR(VLOOKUP(B4,'Materia Prima'!B:E,4,FALSE),0) | F4: =C4*E4
A5: TOTAL | F5: =SUM(F4:F4) | G5: 10 | I5: =IF(G5>0,F5/G5,0)
A7: Cebolla Morada | G7: 20 | H7: tanda
B8: Vinagre en Galon | C8: 150 | D8: litro | E8: =IFERROR(VLOOKUP(B8,'Materia Prima'!B:E,4,FALSE),0) | F8: =C8*E8
B9: Cebolla morada (saco 50 lb) | C9: 1 | D9: lb | E9: =IFERROR(VLOOKUP(B9,'Materia Prima'!B:E,4,FALSE),0) | F9: =C9*E9
B10: Bolsa de hielo 5 lbs | C10: 1 | D10: bolsa | E10: =IFERROR(VLOOKUP(B10,'Materia Prima'!B:E,4,FALSE),0) | F10: =C10*E10
A11: TOTAL | F11: =SUM(F8:F10) | G11: 20 | I11: =IF(G11>0,F11/G11,0)
A13: Cheddar Porcionado (Bolsa 2lb) | G13: 3 | H13: bolsa
B14: Cheddar Lata | C14: 1 | D14: lata | E14: =IFERROR(VLOOKUP(B14,'Materia Prima'!B:E,4,FALSE),0) | F14: =C14*E14
A15: TOTAL | F15: =SUM(F14:F14) | G15: 3 | I15: =IF(G15>0,F15/G15,0)
A17: Chili | G17: 4 | H17: bolsa
B18: 326235 Azucar Morena | C18: 1.35 | D18: g | E18: =IFERROR(VLOOKUP(B18,'Materia Prima'!B:E,4,FALSE),0) | F18: =C18*E18
B19: Chile Chipotle Adobado 24/380 GR | C19: 2 | D19: lata | E19: =IFERROR(VLOOKUP(B19,'Materia Prima'!B:E,4,FALSE),0) | F19: =C19*E19
B20: Cebollas Blancas | C20: 2 | D20: unidad | E20: =IFERROR(VLOOKUP(B20,'Materia Prima'!B:E,4,FALSE),0) | F20: =C20*E20
B21: Zanahoria | C21: 1 | D21: unidad | E21: =IFERROR(VLOOKUP(B21,'Materia Prima'!B:E,4,FALSE),0) | F21: =C21*E21
B22: 55334 MS Paprika | C22: 20 | D22: g | E22: =IFERROR(VLOOKUP(B22,'Materia Prima'!B:E,4,FALSE),0) | F22: =C22*E22
B23: 55331 Pimienta Molida | C23: 1.35 | D23: g | E23: =IFERROR(VLOOKUP(B23,'Materia Prima'!B:E,4,FALSE),0) | F23: =C23*E23
B24: Vinagre en Galon | C24: 0.25 | D24: litro | E24: =IFERROR(VLOOKUP(B24,'Materia Prima'!B:E,4,FALSE),0) | F24: =C24*E24
B25: Chile Molido | C25: 3 | D25: cucharada | E25: =IFERROR(VLOOKUP(B25,'Materia Prima'!B:E,4,FALSE),0) | F25: =C25*E25
B26: Polvo de Hongo | C26: 1 | D26: cucharadita | E26: =IFERROR(VLOOKUP(B26,'Materia Prima'!B:E,4,FALSE),0) | F26: =C26*E26
B27: Caldo de Res en Polvo | C27: 2 | D27: cucharada | E27: =IFERROR(VLOOKUP(B27,'Materia Prima'!B:E,4,FALSE),0) | F27: =C27*E27
B28: 524550 Ajo Granulado | C28: 8 | D28: g | E28: =IFERROR(VLOOKUP(B28,'Materia Prima'!B:E,4,FALSE),0) | F28: =C28*E28
B29: 535 Gran Onion | C29: 8 | D29: g | E29: =IFERROR(VLOOKUP(B29,'Materia Prima'!B:E,4,FALSE),0) | F29: =C29*E29
... B39: Acido Ascorbico | C39: 0.00135 | D39: kg | E39: =IFERROR(VLOOKUP(B39,'Materia Prima'!B:E,4,FALSE),0) | F39: =C39*E39
A40: TOTAL | F40: =SUM(F18:F39) | G40: 4 | I40: =IF(G40>0,F40/G40,0)
A42: Escabeche | G42: 5 | H42: bolsa
B43: Bultos de repollo | C43: 5 | D43: unidad | E43: =IFERROR(VLOOKUP(B43,'Materia Prima'!B:E,4,FALSE),0) | F43: =C43*E43
B44: Zanahoria | C44: 2 | D44: unidad | E44: =IFERROR(VLOOKUP(B44,'Materia Prima'!B:E,4,FALSE),0) | F44: =C44*E44
B45: Mostaza MC Cormick Galon Bolsa | C45: 30 | D45: ml | E45: =IFERROR(VLOOKUP(B45,'Materia Prima'!B:E,4,FALSE),0) | F45: =C45*E45
B46: Vinagre en Galon | C46: 0.5 | D46: litro | E46: =IFERROR(VLOOKUP(B46,'Materia Prima'!B:E,4,FALSE),0) | F46: =C46*E46
B47: 535 Gran Onion | C47: 16 | D47: g | E47: =IFERROR(VLOOKUP(B47,'Materia Prima'!B:E,4,FALSE),0) | F47: =C47*E47
B48: Sazonador Completo MCCormick 2kgs Bolsa | C48: 8 | D48: g | E48: =IFERROR(VLOOKUP(B48,'Materia Prima'!B:E,4,FALSE),0) | F48: =C48*E48
A49: TOTAL | F49: =SUM(F43:F48) | G49: 5 | I49: =IF(G49>0,F49/G49,0)
A51: Fancy | G51: 1 | H51: porcion
B52: Papa Blanca 20lb | C52: 0.35 | D52: lb | E52: =IFERROR(VLOOKUP(B52,'Materia Prima'!B:E,4,FALSE),0) | F52: =C52*E52
B53: Papa Sazonadas 30lb | C53: 0.7 | D53: libra | E53: =IFERROR(VLOOKUP(B53,'Materia Prima'!B:E,4,FALSE),0) | F53: =C53*E53
B54: Papa Waffle 27LB | C54: 0.4 | D54: lb | E54: =IFERROR(VLOOKUP(B54,'Materia Prima'!B:E,4,FALSE),0) | F54: =C54*E54
A55: TOTAL | F55: =SUM(F52:F54) | G55: 1 | I55: =IF(G55>0,F55/G55,0)
A57: Freakie Dog armado | G57: 1 | H57: unidad
B58: Pan Hot Dog Berna bolsa 10 unidades | C58: 1 | D58: bolsa | E58: =IFERROR(VLOOKUP(B58,'Materia Prima'!B:E,4,FALSE),0) | F58: =C58*E58*0.1
B59: Salchicha Parowsi paquete 25 unidades | C59: 1 | D59: paquete | E59: =IFERROR(VLOOKUP(B59,'Materia Prima'!B:E,4,FALSE),0) | F59: =C59*E59*0.04
B60: Mayonesa Hellmans Real | C60: 0.2 | D60: oz | E60: =IFERROR(VLOOKUP(B60,'Materia Prima'!B:E,4,FALSE),0) | F60: =C60*E60
B61: Salsa Ketchup GL. 4X3.5 KG MC Cormick | C61: 0.2 | D61: oz | E61: =IFERROR(VLOOKUP(B61,'Materia Prima'!B:E,4,FALSE),0) | F61: =C61*E61
B62: Pepinillo triturado bote | C62: 0.5 | D62: bote | E62: =IFERROR(VLOOKUP(B62,'Materia Prima'!B:E,4,FALSE),0) | F62: =C62*E62
B63: ↪ Cebolla Blanca | C63: 0.03125 | D63: bolsa | E63: 13.2134 | F63: =C63*E63
B64: ↪ Escabeche | C64: 0.020833333 | D64: bolsa | E64: 11.6007 | F64: =C64*E64
B65: ↪ Salsa Chipotle | C65: 0.015625 | D65: bolsa | E65: 46.935 | F65: =C65*E65
B66: ↪ Cheddar Porcionado (Bolsa 2lb) | C66: 0.5 | D66: bolsa | E66: 10.3451 | F66: =C66*E66*0.03125
A67: TOTAL | F67: =SUM(F58:F66) | G67: 1 | I67: =IF(G67>0,F67/G67,0)
A69: Hamburguesa Sencilla (armada) | G69: 1 | H69: unidad
B70: 228941 Pepinillos | C70: 0.85 | D70: oz | E70: =IFERROR(VLOOKUP(B70,'Materia Prima'!B:E,4,FALSE),0) | F70: =C70*E70
B71: 95816 Mantequilla | C71: 0.5 | D71: g | E71: =IFERROR(VLOOKUP(B71,'Materia Prima'!B:E,4,FALSE),0) | F71: =C71*E71
B72: ↪ Mezcla de Carne Smash | C72: 2 | D72: unidad | E72: 507.1396 | F72: =C72*E72
B73: Pan de Hamburguesa Brioche bolsa 12 unidades | C73: 1 | D73: bolsa | E73: =IFERROR(VLOOKUP(B73,'Materia Prima'!B:E,4,FALSE),0) | F73: =C73*E73*0.083333
B74: MQ LAC Procesado Reb AM C 1.4kg/3lb | C74: 0.0485 | D74: lb | E74: =IFERROR(VLOOKUP(B74,'Materia Prima'!B:E,4,FALSE),0) | F74: =C74*E74
B75: ↪ Sal de Hamburguesa | C75: 0.002 | D75: bolsa | E75: 6.5999 | F75: =C75*E75
B76: ↪ Cebolla Morada | C76: 0.014697917 | D76: tanda | E76: 89.0702 | F76: =C76*E76
B77: ↪ Salsa Mil Islas | C77: 0.0625 | D77: bolsa | E77: 36.7513 | F77: =C77*E77
A78: TOTAL | F78: =SUM(F70:F77) | G78: 1 | I78: =IF(G78>0,F78/G78,0)
A80: Mermelada de Tocino | G80: 4 | H80: tanda
B81: Vinagre de Manzana 1/4 Galon | C81: 1.5625 | D81: cuarto_galón | E81: =IFERROR(VLOOKUP(B81,'Materia Prima'!B:E,4,FALSE),0) | F81: =C81*E81
B82: 326235 Azucar Morena | C82: 1430 | D82: g | E82: =IFERROR(VLOOKUP(B82,'Materia Prima'!B:E,4,FALSE),0) | F82: =C82*E82
B83: 921290 Salsa Soya | C83: 0.015625 | D83: galón | E83: =IFERROR(VLOOKUP(B83,'Materia Prima'!B:E,4,FALSE),0) | F83: =C83*E83
B84: Miel de Maple | C84: 6.33 | D84: taza | E84: =IFERROR(VLOOKUP(B84,'Materia Prima'!B:E,4,FALSE),0) | F84: =C84*E84
B85: 95816 Mantequilla | C85: 0.5 | D85: g | E85: =IFERROR(VLOOKUP(B85,'Materia Prima'!B:E,4,FALSE),0) | F85: =C85*E85
B86: Cebollas Blancas | C86: 25 | D86: unidad | E86: =IFERROR(VLOOKUP(B86,'Materia Prima'!B:E,4,FALSE),0) | F86: =C86*E86
B87: Tocino Ahumado Chimex kg | C87: 1.5876 | D87: kg | E87: =IFERROR(VLOOKUP(B87,'Materia Prima'!B:E,4,FALSE),0) | F87: =C87*E87
A88: TOTAL | F88: =SUM(F81:F87) | G88: 4 | I88: =IF(G88>0,F88/G88,0)
A90: Mezcla de Carne Smash | G90: 650 | H90: unidad
B91: 55331 Pimienta Molida | C91: 10.5 | D91: g | E91: =IFERROR(VLOOKUP(B91,'Materia Prima'!B:E,4,FALSE),0) | F91: =C91*E91
B92: Glutamato Monosodico | C92: 70 | D92: g | E92: =IFERROR(VLOOKUP(B92,'Materia Prima'!B:E,4,FALSE),0) | F92: =C92*E92
B93: 524550 Ajo Granulado | C93: 49 | D93: g | E93: =IFERROR(VLOOKUP(B93,'Materia Prima'!B:E,4,FALSE),0) | F93: =C93*E93
B94: 535 Gran Onion | C94: 56 | D94: g | E94: =IFERROR(VLOOKUP(B94,'Materia Prima'!B:E,4,FALSE),0) | F94: =C94*E94
B95: Nuca de Cerdo | C95: 15 | D95: lb | E95: =IFERROR(VLOOKUP(B95,'Materia Prima'!B:E,4,FALSE),0) | F95: =C95*E95
B96: 2032 Puyazo Gold | C96: 15 | D96: lb | E96: =IFERROR(VLOOKUP(B96,'Materia Prima'!B:E,4,FALSE),0) | F96: =C96*E96
B97: Molida 90/10 | C97: 7.5 | D97: lb | E97: =IFERROR(VLOOKUP(B97,'Materia Prima'!B:E,4,FALSE),0) | F97: =C97*E97
B98: I+G Inosinato Guanilato | C98: 3.5 | D98: g | E98: =IFERROR(VLOOKUP(B98,'Materia Prima'!B:E,4,FALSE),0) | F98: =C98*E98
B99: New York Corte Argentino | C99: 45 | D99: lb | E99: =IFERROR(VLOOKUP(B99,'Materia Prima'!B:E,4,FALSE),0) | F99: =C99*E99
B100: Asado de Tira Corte Argentino | C100: 15 | D100: lb | E100: =IFERROR(VLOOKUP(B100,'Materia Prima'!B:E,4,FALSE),0) | F100: =C100*E100
A101: TOTAL | F101: =SUM(F91:F100) | G101: 650 | I101: =IF(G101>0,F101/G101,0)
A103: Mini Fancy | G103: 1 | H103: porcion
B104: Papa Blanca 20lb | C104: 0.35 | D104: lb | E104: =IFERROR(VLOOKUP(B104,'Materia Prima'!B:E,4,FALSE),0) | F104: =C104*E104
B105: Papa Waffle 27LB | C105: 0.35 | D105: lb | E105: =IFERROR(VLOOKUP(B105,'Materia Prima'!B:E,4,FALSE),0) | F105: =C105*E105
A106: TOTAL | F106: =SUM(F104:F105) | G106: 1 | I106: =IF(G106>0,F106/G106,0)
A108: Papa Blanca | G108: 1 | H108: porcion
B109: Papa Blanca 20lb | C109: 0.35 | D109: lb | E109: =IFERROR(VLOOKUP(B109,'Materia Prima'!B:E,4,FALSE),0) | F109: =C109*E109
A110: TOTAL | F110: =SUM(F109:F109) | G110: 1 | I110: =IF(G110>0,F110/G110,0)
A112: Papa Sazonada | G112: 1 | H112: porcion
B113: Papa Sazonadas 30lb | C113: 0.35 | D113: libra | E113: =IFERROR(VLOOKUP(B113,'Materia Prima'!B:E,4,FALSE),0) | F113: =C113*E113
A114: TOTAL | F114: =SUM(F113:F113) | G114: 1 | I114: =IF(G114>0,F114/G114,0)
A116: Papa Waffle | G116: 1 | H116: porcion
B117: Papa Waffle 27LB | C117: 0.35 | D117: lb | E117: =IFERROR(VLOOKUP(B117,'Materia Prima'!B:E,4,FALSE),0) | F117: =C117*E117
A118: TOTAL | F118: =SUM(F117:F117) | G118: 1 | I118: =IF(G118>0,F118/G118,0)
A120: Ranch Porcionado | G120: 1 | H120: bote
B121: Ranch 1 Galon | C121: 1 | D121: oz | E121: =IFERROR(VLOOKUP(B121,'Materia Prima'!B:E,4,FALSE),0) | F121: =C121*E121
A122: TOTAL | F122: =SUM(F121:F121) | G122: 1 | I122: =IF(G122>0,F122/G122,0)
A124: Sal de Hamburguesa | G124: 1 | H124: bolsa
...

Sheet BOM Menú
A1: Nombre del ítem de menú | B1: Componente (ingrediente o sub-receta) | C1: Tipo: ingrediente (de MP) o sub_receta (de Sub-Productos) | D1: Cantidad por porción vendida | E1: Unidad | F1: Factor de conversión a stock (si aplica) | G1: =precio del ingrediente o costo/porción de sub-receta | H1: =cantidad × costo_unit × factor | I1: Precio de venta al público | J1: =SUM de costo_linea por ítem | K1: =(precio - costo) / precio × 100
A2: menu_item | B2: componente | C2: tipo | D2: cantidad | E2: unidad | F2: factor | G2: costo_unit | H2: costo_linea | I2: precio_venta | J2: costo_total | K2: margen_%
A3: Adivina la Marca | I3: 0 | J3: =SUM(H4:H5) | K3: =IF(I3>0,(I3-J3)/I3*100,0)
B4: Adivina la Maraca paquete 20 Unidades | C4: ingrediente | D4: 20 | E4: bolsa | G4: =IFERROR(VLOOKUP(B4,'Materia Prima'!B:E,4,FALSE),0) | H4: =D4*G4
B5: Mano de obra armado Adivina la Marca | C5: ingrediente | D5: 1 | E5: unidad | G5: =IFERROR(VLOOKUP(B5,'Materia Prima'!B:E,4,FALSE),0) | H5: =D5*G5
A7: Agrandado Soda y Papa | I7: 0 | J7: =SUM(H8:H8) | K7: =IF(I7>0,(I7-J7)/I7*100,0)
B8: Papa Sazonada | C8: sub_receta | D8: 1 | E8: porcion | G8: ='Sub-Productos'!I114 | H8: =D8*G8
A10: Aros de Cebolla | I10: 4.18 | J10: =SUM(H11:H12) | K10: =IF(I10>0,(I10-J10)/I10*100,0)
B11: Aros de cebolla unidad | C11: ingrediente | D11: 1 | E11: porcion | G11: =IFERROR(VLOOKUP(B11,'Materia Prima'!B:E,4,FALSE),0) | H11: =D11*G11
B12: Ranch 1 Galon | C12: ingrediente | D12: 0.015625 | E12: oz | G12: =IFERROR(VLOOKUP(B12,'Materia Prima'!B:E,4,FALSE),0) | H12: =D12*G12
A14: Burger Box | I14: 0 | J14: =SUM(H15:H18) | K14: =IF(I14>0,(I14-J14)/I14*100,0)
B15: Hamburguesa Sencilla (armada) | C15: sub_receta | D15: 2 | E15: unidad | G15: ='Sub-Productos'!I78 | H15: =D15*G15
B16: Freakie Dog armado | C16: sub_receta | D16: 2 | E16: unidad | G16: ='Sub-Productos'!I67 | H16: =D16*G16
B17: Papa Sazonada | C17: sub_receta | D17: 2 | E17: porcion | G17: ='Sub-Productos'!I114 | H17: =D17*G17
B18: Pepperonchini En Vinagre Monteverde BI. PI. H2.2KG | C18: ingrediente | D18: 2 | E18: unidad | G18: =IFERROR(VLOOKUP(B18,'Materia Prima'!B:E,4,FALSE),0) | H18: =D18*G18
A20: Burger Duo | I20: 0 | J20: =SUM(H21:H22) | K20: =IF(I20>0,(I20-J20)/I20*100,0)
B21: Hamburguesa Sencilla (armada) | C21: sub_receta | D21: 2 | E21: unidad | G21: ='Sub-Productos'!I78 | H21: =D21*G21
B22: Papa Sazonada | C22: sub_receta | D22: 2 | E22: porcion | G22: ='Sub-Productos'!I114 | H22: =D22*G22
A24: Chili Duo | I24: 0 | J24: =SUM(H25:H30) | K24: =IF(I24>0,(I24-J24)/I24*100,0)
B25: Chilli dog individual | C25: sub_receta | D25: 2 | E25: porcion | G25: 0.7159 | H25: =D25*G25
B26: Chili | C26: sub_receta | D26: 0.25 | E26: bolsa | G26: ='Sub-Productos'!I40 | H26: =D26*G26
B27: Aros de Cebolla | C27: sub_receta | D27: 1 | E27: porcion | G27: 0.2016 | H27: =D27*G27
B28: Papa Sazonada | C28: sub_receta | D28: 2 | E28: porcion | G28: ='Sub-Productos'!I114 | H28: =D28*G28
B29: Cebolla Blanca | C29: sub_receta | D29: 0.0625 | E29: bolsa | G29: ='Sub-Productos'!I5 | H29: =D29*G29
B30: Jalapeños bote | C30: ingrediente | D30: 2 | E30: oz | G30: =IFERROR(VLOOKUP(B30,'Materia Prima'!B:E,4,FALSE),0) | H30: =D30*G30
A32: Chili Mini Fancys | I32: 0 | J32: =SUM(H33:H34) | K32: =IF(I32>0,(I32-J32)/I32*100,0)
B33: Mini Fancy | C33: sub_receta | D33: 1 | E33: porcion | G33: ='Sub-Productos'!I106 | H33: =D33*G33
B34: Chili | C34: sub_receta | D34: 0.0625 | E34: bolsa | G34: ='Sub-Productos'!I40 | H34: =D34*G34
A36: Chili Mini Fancys | I36: 4.99 | J36: 0 | K36: =IF(I36>0,(I36-J36)/I36*100,0)
A38: Chili porción | I38: 0 | J38: =SUM(H39:H39) | K38: =IF(I38>0,(I38-J38)/I38*100,0)
B39: Chili | C39: sub_receta | D39: 0.125 | E39: bolsa | G39: ='Sub-Productos'!I40 | H39: =D39*G39
A41: Chilli Dog | I41: 0 | J41: =SUM(H42:H42) | K41: =IF(I41>0,(I41-J41)/I41*100,0)
B42: Chilli dog individual | C42: sub_receta | D42: 1 | E42: porcion | G42: 0.7159 | H42: =D42*G42
A44: Chilli dog individual | I44: 2.99 | J44: =SUM(H45:H48) | K44: =IF(I44>0,(I44-J44)/I44*100,0)
B45: Cheddar Porcionado (Bolsa 2lb) | C45: sub_receta | D45: 1 | E45: bolsa | F45: 0.03125 | G45: ='Sub-Productos'!I15 | H45: =D45*G45*F45
B46: Salchicha Parowsi paquete 25 unidades | C46: ingrediente | D46: 1 | E46: paquete | F46: 0.04 | G46: =IFERROR(VLOOKUP(B46,'Materia Prima'!B:E,4,FALSE),0) | H46: =D46*G46*F46
B47: Pan Hot Dog Berna bolsa 10 unidades | C47: ingrediente | D47: 1 | E47: bolsa | F47: 0.1 | G47: =IFERROR(VLOOKUP(B47,'Materia Prima'!B:E,4,FALSE),0) | H47: =D47*G47*F47
B48: Chili | C48: sub_receta | D48: 0.0625 | E48: bolsa | G48: ='Sub-Productos'!I40 | H48: =D48*G48
A50: Coca-Cola Combo | I50: 0 | J50: =SUM(H51:H52) | K50: =IF(I50>0,(I50-J50)/I50*100,0)
B51: Freakie Dog armado | C51: sub_receta | D51: 1 | E51: unidad | G51: ='Sub-Productos'!I67 | H51: =D51*G51
B52: Papa Sazonada | C52: sub_receta | D52: 1 | E52: porcion | G52: ='Sub-Productos'!I114 | H52: =D52*G52
A54: Coca-Cola Combo XL | I54: 0 | J54: =SUM(H55:H57) | K54: =IF(I54>0,(I54-J54)/I54*100,0)
B55: Freakie Dog armado | C55: sub_receta | D55: 2 | E55: unidad | G55: ='Sub-Productos'!I67 | H55: =D55*G55
B56: Papa Sazonada | C56: sub_receta | D56: 1 | E56: porcion | G56: ='Sub-Productos'!I114 | H56: =D56*G56
B57: Jalapeños bote | C57: ingrediente | D57: 2 | E57: oz | G57: =IFERROR(VLOOKUP(B57,'Materia Prima'!B:E,4,FALSE),0) | H57: =D57*G57
A59: Combig | I59: 0 | J59: =SUM(H60:H65) | K59: =IF(I59>0,(I59-J59)/I59*100,0)
B60: Hamburguesa Sencilla (armada) | C60: sub_receta | D60: 2 | E60: unidad | G60: ='Sub-Productos'!I78 | H60: =D60*G60
B61: Freakie Dog armado | C61: sub_receta | D61: 2 | E61: unidad | G61: ='Sub-Productos'!I67 | H61: =D61*G61
B62: Queso para dorar | C62: ingrediente | D62: 0.3 | E62: lb | G62: =IFERROR(VLOOKUP(B62,'Materia Prima'!B:E,4,FALSE),0) | H62: =D62*G62
B63: Papa Sazonada | C63: sub_receta | D63: 2 | E63: porcion | G63: ='Sub-Productos'!I114 | H63: =D63*G63
B64: PAPA WAFFLE NAT CAJA 6/4.5 LBS | C64: ingrediente | D64: 0.35 | E64: libra | G64: =IFERROR(VLOOKUP(B64,'Materia Prima'!B:E,4,FALSE),0) | H64: =D64*G64
B65: Papa Blanca 20lb | C65: ingrediente | D65: 0.35 | E65: lb | G65: =IFERROR(VLOOKUP(B65,'Materia Prima'!B:E,4,FALSE),0) | H65: =D65*G65
A67: Combo Chilli Dog | I67: 0 | J67: =SUM(H68:H70) | K67: =IF(I67>0,(I67-J67)/I67*100,0)
B68: Freakie Dog armado | C68: sub_receta | D68: 1 | E68: unidad | G68: ='Sub-Productos'!I67 | H68: =D68*G68
B69: Papa Sazonada | C69: sub_receta | D69: 1 | E69: porcion | G69: ='Sub-Productos'!I114 | H69: =D69*G69
B70: Chili | C70: sub_receta | D70: 0.0625 | E70: bolsa | G70: ='Sub-Productos'!I40 | H70: =D70*G70
A72: Combo Chilli Dog | I72: 6.08 | J72: 0 | K72: =IF(I72>0,(I72-J72)/I72*100,0)
A74: Combo Duo | I74: 0 | J74: =SUM(H75:H76) | K74: =IF(I74>0,(I74-J74)/I74*100,0)
B75: Freakie Dog armado | C75: sub_receta | D75: 2 | E75: unidad | G75: ='Sub-Productos'!I67 | H75: =D75*G75
B76: Papa Sazonada | C76: sub_receta | D76: 2 | E76: porcion | G76: ='Sub-Productos'!I114 | H76: =D76*G76
A78: Combo Fancy Duo | I78: 0 | J78: =SUM(H79:H81) | K78: =IF(I78>0,(I78-J78)/I78*100,0)
B79: Freakie Dog armado | C79: sub_receta | D79: 2 | E79: unidad | G79: ='Sub-Productos'!I67 | H79: =D79*G79
B80: PAPA WAFFLE NAT CAJA 6/4.5 LBS | C80: ingrediente | D80: 0.35 | E80: libra | G80: =IFERROR(VLOOKUP(B80,'Materia Prima'!B:E,4,FALSE),0) | H80: =D80*G80
B81: Papa Blanca 20lb | C81: ingrediente | D81: 0.35 | E81: lb | G81: =IFERROR(VLOOKUP(B81,'Materia Prima'!B:E,4,FALSE),0) | H81: =D81*G81
A83: Combo Freakie Dog | I83: 4.08 | J83: =SUM(H84:H88) | K83: =IF(I83>0,(I83-J83)/I83*100,0)
B84: Escabeche | C84: sub_receta | D84: 1 | E84: bolsa | G84: ='Sub-Productos'!I49 | H84: =D84*G84
B85: 325026-MCX03621 MC REDSTONE | C85: ingrediente | D85: 0.024 | E85: Caja | G85: =IFERROR(VLOOKUP(B85,'Materia Prima'!B:E,4,FALSE),0) | H85: =D85*G85
B86: Gaseosa Coca-Cola Vr 354ml 1x24 un | C86: ingrediente | D86: 1 | E86: Caja | G86: =IFERROR(VLOOKUP(B86,'Materia Prima'!B:E,4,FALSE),0) | H86: =D86*G86
B87: Salchicha Parowsi paquete 25 unidades | C87: ingrediente | D87: 1 | E87: paquete | F87: 0.04 | G87: =IFERROR(VLOOKUP(B87,'Materia Prima'!B:E,4,FALSE),0) | H87: =D87*G87*F87
B88: Pan Hot Dog Berna bolsa 10 unidades | C88: ingrediente | D88: 1 | E88: bolsa | F88: 0.1 | G88: =IFERROR(VLOOKUP(B88,'Materia Prima'!B:E,4,FALSE),0) | H88: =D88*G88*F88
A90: Combo Freakie Dog | I90: 0 | J90: =SUM(H91:H92) | K90: =IF(I90>0,(I90-J90)/I90*100,0)
B91: Freakie Dog armado | C91: sub_receta | D91: 1 | E91: unidad | G91: ='Sub-Productos'!I67 | H91: =D91*G91
B92: Papa Sazonada | C92: sub_receta | D92: 1 | E92: porcion | G92: ='Sub-Productos'!I114 | H92: =D92*G92
A94: Combo Hamburguesa | I94: 8.48 | J94: =SUM(H95:H102) | K94: =IF(I94>0,(I94-J94)/I94*100,0)
B95: Cebolla Roja | C95: ingrediente | D95: 0.02 | E95: saco | G95: =IFERROR(VLOOKUP(B95,'Materia Prima'!B:E,4,FALSE),0) | H95: =D95*G95
B96: MQ LAC Procesado Reb AM C 1.4kg/3lb | C96: ingrediente | D96: 0.33 | E96: lb | G96: =IFERROR(VLOOKUP(B96,'Materia Prima'!B:E,4,FALSE),0) | H96: =D96*G96
B97: 16100 Pepinillos | C97: ingrediente | D97: 0.02 | E97: Unidad | G97: =IFERROR(VLOOKUP(B97,'Materia Prima'!B:E,4,FALSE),0) | H97: =D97*G97
B98: Mezcla de Carne Smash | C98: sub_receta | D98: 2 | E98: unidad | G98: ='Sub-Productos'!I101 | H98: =D98*G98
B99: Pan de Hamburguesa Brioche bolsa 12 unidades | C99: ingrediente | D99: 1 | E99: bolsa | F99: 0.083333 | G99: =IFERROR(VLOOKUP(B99,'Materia Prima'!B:E,4,FALSE),0) | H99: =D99*G99*F99
B100: Sal de Hamburguesa | C100: sub_receta | D100: 1 | E100: bolsa | G100: ='Sub-Productos'!I129 | H100: =D100*G100
B101: Gaseosa Coca-Cola Vr 354ml 1x24 un | C101: ingrediente | D101: 1 | E101: Caja | G101: =IFERROR(VLOOKUP(B101,'Materia Prima'!B:E,4,FALSE),0) | H101: =D101*G101
B102: 325026-MCX03621 MC REDSTONE | C102: ingrediente | D102: 0.024 | E102: Caja | G102: =IFERROR(VLOOKUP(B102,'Materia Prima'!B:E,4,FALSE),0) | H102: =D102*G102
A104: Combo Hamburguesa | I104: 0 | J104: =SUM(H105:H106) | K104: =IF(I104>0,(I104-J104)/I104*100,0)
B105: Hamburguesa Sencilla (armada) | C105: sub_receta | D105: 1 | E105: unidad | G105: ='Sub-Productos'!I78 | H105: =D105*G105
B106: Papa Sazonada | C106: sub_receta | D106: 1 | E106: porcion | G106: ='Sub-Productos'!I114 | H106: =D106*G106
A108: Combo Super Freak | I108: 6.25 | J108: =SUM(H109:H114) | K108: =IF(I108>0,(I108-J108)/I108*100,0)
B109: Sal de Hamburguesa | C109: sub_receta | D109: 1 | E109: bolsa | G109: ='Sub-Productos'!I129 | H109: =D109*G109
B110: Mezcla de Carne Smash | C110: sub_receta | D110: 3 | E110: unidad | G110: ='Sub-Productos'!I101 | H110: =D110*G110
B111: MQ LAC Procesado Reb AM C 1.4kg/3lb | C111: ingrediente | D111: 0.5 | E111: lb | G111: =IFERROR(VLOOKUP(B111,'Materia Prima'!B:E,4,FALSE),0) | H111: =D111*G111
B112: 325026-MCX03621 MC REDSTONE | C112: ingrediente | D112: 0.024 | E112: Caja | G112: =IFERROR(VLOOKUP(B112,'Materia Prima'!B:E,4,FALSE),0) | H112: =D112*G112
B113: Gaseosa Coca-Cola Vr 354ml 1x24 un | C113: ingrediente | D113: 1 | E113: Caja | G113: =IFERROR(VLOOKUP(B113,'Materia Prima'!B:E,4,FALSE),0) | H113: =D113*G113
B114: Pan de Hot Dog Brioche bolsa 12 unidades | C114: ingrediente | D114: 1 | E114: bolsa | F114: 0.083333 | G114: =IFERROR(VLOOKUP(B114,'Materia Prima'!B:E,4,FALSE),0) | H114: =D114*G114*F114
A116: Combo Super Freak | I116: 0 | J116: =SUM(H117:H118) | K116: =IF(I116>0,(I116-J116)/I116*100,0)
B117: Super Freak armado | C117: sub_receta | D117: 1 | E117: unidad | G117: ='Sub-Productos'!I163 | H117: =D117*G117
B118: Papa Sazonada | C118: sub_receta | D118: 1 | E118: porcion | G118: ='Sub-Productos'!I114 | H118: =D118*G118
A120: Combo Trio | I120: 0 | J120: =SUM(H121:H122) | K120: =IF(I120>0,(I120-J120)/I120*100,0)
B121: Freakie Dog armado | C121: sub_receta | D121: 3 | E121: unidad | G121: ='Sub-Productos'!I67 | H121: =D121*G121
B122: Papa Sazonada | C122: sub_receta | D122: 3 | E122: porcion | G122: ='Sub-Productos'!I114 | H122: =D122*G122
A124: Combpleto | I124: 0 | J124: =SUM(H125:H131) | K124: =IF(I124>0,(I124-J124)/I124*100,0)
B125: Hamburguesa Sencilla (armada) | C125: sub_receta | D125: 2 | E125: unidad | G125: ='Sub-Productos'!I78 | H125: =D125*G125
...

Sheet Explicación
A1: Estructura del Excel
A2: Tab Materia Prima | B2: Lista maestra de todos los ingredientes/insumos. Es la fuente de verdad para precios. Los tabs de Sub-Productos y BOM Menú buscan precios aquí con BUSCARV.
A3: Tab Sub-Productos | B3: Recetas de producción (salsas, mezcla de carne, etc.). Cada sección tiene un encabezado con el nombre y rendimiento, seguido de los ingredientes. El costo por porción se calcula automáticamente.
A4: Tab BOM Menú | B4: Bill of Materials de cada ítem del menú. Muestra ingredientes directos + sub-recetas. El costo total y margen se calculan con fórmulas.
A6: Columnas clave
A7: precio_unit (MP) | B7: Precio por 1 unidad de stock. Ej: si el stock es en gramos, es $/gramo. Si es en bolsa, es $/bolsa.
A8: cantidad (SP/BOM) | B8: Cuántas unidades del ingrediente se usan por lote (SP) o por porción vendida (BOM).
A9: factor_a_stock | B9: Convierte la unidad de la receta a la unidad de stock. Ej: 1 hot dog usa 1 salchicha, pero el stock es en paquetes de 25 → factor = 1/25 = 0.04. Si las unidades coinciden, no se pone factor.
A10: costo_linea | B10: =cantidad × precio_unit × factor. Es lo que cuesta ese ingrediente en esta receta.
A11: rendimiento | B11: Cuántas porciones salen de un lote. Ej: Mezcla Carne Smash rinde 650 bolitas por lote de 100 lb.
A12: costo_por_porcion | B12: =costo_total_lote / rendimiento. Es lo que cuesta 1 porción del sub-producto.
A13: margen_% | B13: =(precio_venta - costo_total) / precio_venta × 100.
A15: Celdas amarillas | B15: Contienen fórmulas — se recalculan automáticamente al cambiar ingredientes o precios.
A16: Celdas rojas | B16: Ítems SIN RECETA — necesitan que se les cree una.
A17: Dropdown en ingrediente | B17: Seleccionar de la lista de Materia Prima para que el BUSCARV traiga el precio correcto.
A19: Notas de Cesar (25-ago-2026)
A20: Recetas V3/V4 pendientes | B20: Mezcla Carne Smash V3, Salsa Mil Islas V4, Sal de Hamburguesa, Cebolla Morada V2, Hamburguesa Sencilla. Están en Editor_Recetas_Combo_Hamburguesa.html. NO aplicadas al DB aún.
A21: Errores de unidades | B21: Ranch: precio era por galón pero unidad dice oz. Pepinillos: bote 46oz pero solo 19oz escurridos. Sal: 24× cara. Vinagre: 750× de más. Salsa inglesa: 8.5× de más.
A22: Duplicados | B22: New York (2 filas), Brisket (3,321 lb sin mapear), Cebolla morada (4 filas, 2 ya desactivadas). 6,373 lb de carne ($25K) sin entrar a productos.
A23: Producto faltante | B23: Bionis YE 38 — CREADO 25-ago, necesario para V3 Carne Smash.
